MHcal/__init__.py
MHcal/calculator.py
MHcal-0.1.dist-info/METADATA
MHcal-0.1.dist-info/WHEEL
MHcal-0.1.dist-info/top_level.txt
MHcal-0.1.dist-info/RECORD
