Metadata-Version: 2.1
Name: MHcal
Version: 0.1
Summary: A simple Python library for basic math operations
Author: danishk sinha
Author-email: thisisdanishk@gmail.com
